Metadata-Version: 2.1
Name: opentelemetry-instrumentation-kser
Version: 0.1.0
Summary: OpenTelemetry kser instrumentation
Home-page: https://github.com/cdumay/opentelemetry-instrumentation-kser
Author: Cédric Dumay
Author-email: cedric.dumay@gmail.com
License: BSD 3-Clause License
Platform: any
Classifier: Development Status :: 4 - Beta
Classifier: Intended Audience :: Developers
Classifier: Programming Language :: Python
Classifier: Programming Language :: Python :: 3
Classifier: Programming Language :: Python :: 3.6
Classifier: Programming Language :: Python :: 3.7
Classifier: Programming Language :: Python :: 3.8
Requires-Python: >=3.6
Provides-Extra: test
Provides-Extra: instruments
